jupyter_cell_modifier/__init__.py
jupyter_cell_modifier/install.py
jupyter_cell_modifier/kernel_config.py
jupyter_cell_modifier/magics.py
jupyter_cell_modifier/server_config.py
jupyter_cell_modifier/static/custom/custom.js
jupyter_cell_modifier-0.1.0.data/data/etc/jupyter/jupyter_notebook_config.d/jupyter_cell_modifier.json
jupyter_cell_modifier-0.1.0.data/data/share/jupyter/nbextensions/jupyter_cell_modifier/custom.js
jupyter_cell_modifier-0.1.0.dist-info/METADATA
jupyter_cell_modifier-0.1.0.dist-info/WHEEL
jupyter_cell_modifier-0.1.0.dist-info/entry_points.txt
jupyter_cell_modifier-0.1.0.dist-info/top_level.txt
jupyter_cell_modifier-0.1.0.dist-info/RECORD
